{
  "data": {
    "etcgames": [
      {
        "gday": "20240914",
        "gmkey": "20240914KTOB0",
        "how": "결승타",
        "result": "정수빈(3회 1사 2루서 중전 안타)",
        "seq": 1
      },
      {
        "gday": "20240914",
        "gmkey": "20240914KTOB0",
        "how": "2루타",
        "result": "강승호(2회) 김상수(4회) \r\n\r\n",
        "seq": 4
      },
      {
        "gday": "20240914",
        "gmkey": "20240914KTOB0",
        "how": "실책",
        "result": "곽빈(1회) 고영표(2회) \r\n\r\n",
        "seq": 5
      },
      {
        "gday": "20240914",
        "gmkey": "20240914KTOB0",
        "how": "도루",
        "result": "문상철(1회) 장성우(1회) 정수빈2(3회) \r\n\r\n",
        "seq": 6
      },
      {
        "gday": "20240914",
        "gmkey": "20240914KTOB0",
        "how": "견제사",
        "result": "조수행(5회) \r\n\r\n",
        "seq": 9
      },
      {
        "gday": "20240914",
        "gmkey": "20240914KTOB0",
        "how": "병살타",
        "result": "황재균(6회) \r\n\r\n",
        "seq": 10
      },
      {
        "gday": "20240914",
        "gmkey": "20240914KTOB0",
        "how": "심판",
        "result": "이용혁 윤태수 최영주 이계성",
        "seq": 16
      }
    ],
    "gameFlag": "0",
    "hbatters": [
      {
        "ab": 4,
        "accmAb": 476,
        "accmHit": 135,
        "changeinn": "",
        "gday": "20240914",
        "gmkey": "20240914KTOB0",
        "hit": 2,
        "il1": "",
        "il10": "",
        "il11": "",
        "il12": "",
        "il13": "",
        "il14": "",
        "il15": "",
        "il16": "",
        "il17": "",
        "il18": "",
        "il19": "",
        "il2": "",
        "il20": "",
        "il21": "",
        "il22": "",
        "il23": "",
        "il24": "",
        "il25": "",
        "il3": "",
        "il4": "",
        "il5": "",
        "il6": "",
        "il7": "",
        "il8": "",
        "il9": "",
        "inn1": "우비",
        "inn10": "",
        "inn11": "",
        "inn12": "",
        "inn13": "",
        "inn14": "",
        "inn15": "",
        "inn16": "",
        "inn17": "",
        "inn18": "",
        "inn19": "",
        "inn2": "",
        "inn20": "",
        "inn21": "",
        "inn22": "",
        "inn23": "",
        "inn24": "",
        "inn25": "",
        "inn3": "중안",
        "inn4": "",
        "inn5": "",
        "inn6": "좌안",
        "inn7": "",
        "inn8": "좌비",
        "inn9": "",
        "name": "정수빈",
        "oneturn": "1",
        "pcode": "79231",
        "position": "중",
        "rbi": 1,
        "run": 0,
        "tb": "B",
        "turn": "11"
      },
      {
        "ab": 2,
        "accmAb": 209,
        "accmHit": 61,
        "changeinn": "",
        "gday": "20240914",
        "gmkey": "20240914KTOB0",
        "hit": 0,
        "il1": "",
        "il10": "",
        "il11": "",
        "il12": "",
        "il13": "",
        "il14": "",
        "il15": "",
        "il16": "",
        "il17": "",
        "il18": "",
        "il19": "",
        "il2": "",
        "il20": "",
        "il21": "",
        "il22": "",
        "il23": "",
        "il24": "",
        "il25": "",
        "il3": "",
        "il4": "",
        "il5": "",
        "il6": "",
        "il7": "",
        "il8": "",
        "il9": "",
        "inn1": "유비",
        "inn10": "",
        "inn11": "",
        "inn12": "",
        "inn13": "",
        "inn14": "",
        "inn15": "",
        "inn16": "",
        "inn17": "",
        "inn18": "",
        "inn19": "",
        "inn2": "",
        "inn20": "",
        "inn21": "",
        "inn22": "",
        "inn23": "",
        "inn24": "",
        "inn25": "",
        "inn3": "2땅",
        "inn4": "",
        "inn5": "",
        "inn6": "3희번",
        "inn7": "",
        "inn8": "",
        "inn9": "",
        "name": "이유찬",
        "oneturn": "2",
        "pcode": "67207",
        "position": "좌",
        "rbi": 0,
        "run": 0,
        "tb": "B",
        "turn": "12"
      },
      {
        "ab": 3,
        "accmAb": 414,
        "accmHit": 130,
        "changeinn": "",
        "gday": "20240914",
        "gmkey": "20240914KTOB0",
        "hit": 0,
        "il1": "",
        "il10": "",
        "il11": "",
        "il12": "",
        "il13": "",
        "il14": "",
        "il15": "",
        "il16": "",
        "il17": "",
        "il18": "",
        "il19": "",
        "il2": "",
        "il20": "",
        "il21": "",
        "il22": "",
        "il23": "",
        "il24": "",
        "il25": "",
        "il3": "",
        "il4": "",
        "il5": "",
        "il6": "",
        "il7": "",
        "il8": "",
        "il9": "",
        "inn1": "1땅",
        "inn10": "",
        "inn11": "",
        "inn12": "",
        "inn13": "",
        "inn14": "",
        "inn15": "",
        "inn16": "",
        "inn17": "",
        "inn18": "",
        "inn19": "",
        "inn2": "",
        "inn20": "",
        "inn21": "",
        "inn22": "",
        "inn23": "",
        "inn24": "",
        "inn25": "",
        "inn3": "유땅",
        "inn4": "",
        "inn5": "",
        "inn6": "중비",
        "inn7": "",
        "inn8": "",
        "inn9": "",
        "name": "양의지",
        "oneturn": "3",
        "pcode": "76232",
        "position": "포",
        "rbi": 0,
        "run": 0,
        "tb": "B",
        "turn": "13"
      },
      {
        "ab": 3,
        "accmAb": 435,
        "accmHit": 116,
        "changeinn": "",
        "gday": "20240914",
        "gmkey": "20240914KTOB0",
        "hit": 0,
        "il1": "",
        "il10": "",
        "il11": "",
        "il12": "",
        "il13": "",
        "il14": "",
        "il15": "",
        "il16": "",
        "il17": "",
        "il18": "",
        "il19": "",
        "il2": "",
        "il20": "",
        "il21": "",
        "il22": "",
        "il23": "",
        "il24": "",
        "il25": "",
        "il3": "",
        "il4": "",
        "il5": "",
        "il6": "",
        "il7": "",
        "il8": "",
        "il9": "",
        "inn1": "",
        "inn10": "",
        "inn11": "",
        "inn12": "",
        "inn13": "",
        "inn14": "",
        "inn15": "",
        "inn16": "",
        "inn17": "",
        "inn18": "",
        "inn19": "",
        "inn2": "삼진",
        "inn20": "",
        "inn21": "",
        "inn22": "",
        "inn23": "",
        "inn24": "",
        "inn25": "",
        "inn3": "",
        "inn4": "투땅",
        "inn5": "",
        "inn6": "우비",
        "inn7": "",
        "inn8": "",
        "inn9": "",
        "name": "김재환",
        "oneturn": "4",
        "pcode": "78224",
        "position": "지",
        "rbi": 0,
        "run": 0,
        "tb": "B",
        "turn": "14"
      },
      {
        "ab": 3,
        "accmAb": 500,
        "accmHit": 123,
        "changeinn": "",
        "gday": "20240914",
        "gmkey": "20240914KTOB0",
        "hit": 0,
        "il1": "",
        "il10": "",
        "il11": "",
        "il12": "",
        "il13": "",
        "il14": "",
        "il15": "",
        "il16": "",
        "il17": "",
        "il18": "",
        "il19": "",
        "il2": "",
        "il20": "",
        "il21": "",
        "il22": "",
        "il23": "",
        "il24": "",
        "il25": "",
        "il3": "",
        "il4": "",
        "il5": "",
        "il6": "",
        "il7": "",
        "il8": "",
        "il9": "",
        "inn1": "",
        "inn10": "",
        "inn11": "",
        "inn12": "",
        "inn13": "",
        "inn14": "",
        "inn15": "",
        "inn16": "",
        "inn17": "",
        "inn18": "",
        "inn19": "",
        "inn2": "삼진",
        "inn20": "",
        "inn21": "",
        "inn22": "",
        "inn23": "",
        "inn24": "",
        "inn25": "",
        "inn3": "",
        "inn4": "유땅",
        "inn5": "",
        "inn6": "",
        "inn7": "3땅",
        "inn8": "",
        "inn9": "",
        "name": "양석환",
        "oneturn": "5",
        "pcode": "64153",
        "position": "一",
        "rbi": 0,
        "run": 0,
        "tb": "B",
        "turn": "15"
      },
      {
        "ab": 3,
        "accmAb": 500,
        "accmHit": 142,
        "changeinn": "",
        "gday": "20240914",
        "gmkey": "20240914KTOB0",
        "hit": 1,
        "il1": "",
        "il10": "",
        "il11": "",
        "il12": "",
        "il13": "",
        "il14": "",
        "il15": "",
        "il16": "",
        "il17": "",
        "il18": "",
        "il19": "",
        "il2": "",
        "il20": "",
        "il21": "",
        "il22": "",
        "il23": "",
        "il24": "",
        "il25": "",
        "il3": "",
        "il4": "",
        "il5": "",
        "il6": "",
        "il7": "",
        "il8": "",
        "il9": "",
        "inn1": "",
        "inn10": "",
        "inn11": "",
        "inn12": "",
        "inn13": "",
        "inn14": "",
        "inn15": "",
        "inn16": "",
        "inn17": "",
        "inn18": "",
        "inn19": "",
        "inn2": "중2",
        "inn20": "",
        "inn21": "",
        "inn22": "",
        "inn23": "",
        "inn24": "",
        "inn25": "",
        "inn3": "",
        "inn4": "삼진",
        "inn5": "",
        "inn6": "",
        "inn7": "유비",
        "inn8": "",
        "inn9": "",
        "name": "강승호",
        "oneturn": "6",
        "pcode": "63123",
        "position": "二",
        "rbi": 0,
        "run": 1,
        "tb": "B",
        "turn": "16"
      },
      {
        "ab": 3,
        "accmAb": 400,
        "accmHit": 127,
        "changeinn": "",
        "gday": "20240914",
        "gmkey": "20240914KTOB0",
        "hit": 0,
        "il1": "",
        "il10": "",
        "il11": "",
        "il12": "",
        "il13": "",
        "il14": "",
        "il15": "",
        "il16": "",
        "il17": "",
        "il18": "",
        "il19": "",
        "il2": "",
        "il20": "",
        "il21": "",
        "il22": "",
        "il23": "",
        "il24": "",
        "il25": "",
        "il3": "",
        "il4": "",
        "il5": "",
        "il6": "",
        "il7": "",
        "il8": "",
        "il9": "",
        "inn1": "",
        "inn10": "",
        "inn11": "",
        "inn12": "",
        "inn13": "",
        "inn14": "",
        "inn15": "",
        "inn16": "",
        "inn17": "",
        "inn18": "",
        "inn19": "",
        "inn2": "유땅",
        "inn20": "",
        "inn21": "",
        "inn22": "",
        "inn23": "",
        "inn24": "",
        "inn25": "",
        "inn3": "",
        "inn4": "",
        "inn5": "삼진",
        "inn6": "",
        "inn7": "우비",
        "inn8": "",
        "inn9": "",
        "name": "허경민",
        "oneturn": "7",
        "pcode": "79240",
        "position": "三",
        "rbi": 0,
        "run": 0,
        "tb": "B",
        "turn": "17"
      },
      {
        "ab": 3,
        "accmAb": 101,
        "accmHit": 29,
        "changeinn": "",
        "gday": "20240914",
        "gmkey": "20240914KTOB0",
        "hit": 1,
        "il1": "",
        "il10": "",
        "il11": "",
        "il12": "",
        "il13": "",
        "il14": "",
        "il15": "",
        "il16": "",
        "il17": "",
        "il18": "",
        "il19": "",
        "il2": "",
        "il20": "",
        "il21": "",
        "il22": "",
        "il23": "",
        "il24": "",
        "il25": "",
        "il3": "",
        "il4": "",
        "il5": "",
        "il6": "",
        "il7": "",
        "il8": "",
        "il9": "",
        "inn1": "",
        "inn10": "",
        "inn11": "",
        "inn12": "",
        "inn13": "",
        "inn14": "",
        "inn15": "",
        "inn16": "",
        "inn17": "",
        "inn18": "",
        "inn19": "",
        "inn2": "",
        "inn20": "",
        "inn21": "",
        "inn22": "",
        "inn23": "",
        "inn24": "",
        "inn25": "",
        "inn3": "중안",
        "inn4": "",
        "inn5": "투직",
        "inn6": "",
        "inn7": "",
        "inn8": "좌비",
        "inn9": "",
        "name": "김재호",
        "oneturn": "8",
        "pcode": "74206",
        "position": "유",
        "rbi": 0,
        "run": 1,
        "tb": "B",
        "turn": "18"
      },
      {
        "ab": 1,
        "accmAb": 303,
        "accmHit": 80,
        "changeinn": "",
        "gday": "20240914",
        "gmkey": "20240914KTOB0",
        "hit": 0,
        "il1": "",
        "il10": "",
        "il11": "",
        "il12": "",
        "il13": "",
        "il14": "",
        "il15": "",
        "il16": "",
        "il17": "",
        "il18": "",
        "il19": "",
        "il2": "",
        "il20": "",
        "il21": "",
        "il22": "",
        "il23": "",
        "il24": "",
        "il25": "",
        "il3": "",
        "il4": "",
        "il5": "",
        "il6": "",
        "il7": "",
        "il8": "",
        "il9": "",
        "inn1": "",
        "inn10": "",
        "inn11": "",
        "inn12": "",
        "inn13": "",
        "inn14": "",
        "inn15": "",
        "inn16": "",
        "inn17": "",
        "inn18": "",
        "inn19": "",
        "inn2": "",
        "inn20": "",
        "inn21": "",
        "inn22": "",
        "inn23": "",
        "inn24": "",
        "inn25": "",
        "inn3": "투희번",
        "inn4": "",
        "inn5": "4구",
        "inn6": "",
        "inn7": "",
        "inn8": "우비",
        "inn9": "",
        "name": "조수행",
        "oneturn": "9",
        "pcode": "66209",
        "position": "우",
        "rbi": 0,
        "run": 0,
        "tb": "B",
        "turn": "19"
      },
      {
        "ab": 25,
        "accmAb": 0,
        "accmHit": 0,
        "changeinn": "",
        "gday": "20240914",
        "gmkey": "20240914KTOB0",
        "hit": 4,
        "il1": "",
        "il10": "",
        "il11": "",
        "il12": "",
        "il13": "",
        "il14": "",
        "il15": "",
        "il16": "",
        "il17": "",
        "il18": "",
        "il19": "",
        "il2": "",
        "il20": "",
        "il21": "",
        "il22": "",
        "il23": "",
        "il24": "",
        "il25": "",
        "il3": "",
        "il4": "",
        "il5": "",
        "il6": "",
        "il7": "",
        "il8": "",
        "il9": "",
        "inn1": "",
        "inn10": "",
        "inn11": "",
        "inn12": "",
        "inn13": "",
        "inn14": "",
        "inn15": "",
        "inn16": "",
        "inn17": "",
        "inn18": "",
        "inn19": "",
        "inn2": "",
        "inn20": "",
        "inn21": "",
        "inn22": "",
        "inn23": "",
        "inn24": "",
        "inn25": "",
        "inn3": "",
        "inn4": "",
        "inn5": "",
        "inn6": "",
        "inn7": "",
        "inn8": "",
        "inn9": "",
        "name": "합계",
        "oneturn": "",
        "pcode": "b",
        "position": "",
        "rbi": 1,
        "run": 2,
        "tb": "b",
        "turn": ""
      }
    ],
    "hpitchers": [
      {
        "ab": 16,
        "accmEr": 72,
        "accmInn2": 469,
        "bbhp": 5,
        "bf": 90,
        "changeinn": "",
        "er": 0,
        "game": 28,
        "gday": "20240914",
        "gmkey": "20240914KTOB0",
        "hit": 2,
        "hr": 0,
        "inn": "5",
        "kk": 5,
        "l": 9,
        "name": "곽빈",
        "pa": 22,
        "pcode": "68220",
        "pos": "11",
        "r": 1,
        "s": 0,
        "tb": "B",
        "w": 13,
        "wls": "W"
      },
      {
        "ab": 5,
        "accmEr": 26,
        "accmInn2": 176,
        "bbhp": 0,
        "bf": 18,
        "changeinn": "6.5",
        "er": 0,
        "game": 53,
        "gday": "20240914",
        "gmkey": "20240914KTOB0",
        "hit": 1,
        "hr": 0,
        "inn": "1 ⅔",
        "kk": 0,
        "l": 4,
        "name": "이영하",
        "pa": 5,
        "pcode": "66291",
        "pos": "21",
        "r": 0,
        "s": 2,
        "tb": "B",
        "w": 4,
        "wls": "H"
      },
      {
        "ab": 2,
        "accmEr": 21,
        "accmInn2": 186,
        "bbhp": 1,
        "bf": 13,
        "changeinn": "7.1",
        "er": 0,
        "game": 72,
        "gday": "20240914",
        "gmkey": "20240914KTOB0",
        "hit": 0,
        "hr": 0,
        "inn": "0 ⅔",
        "kk": 1,
        "l": 1,
        "name": "이병헌",
        "pa": 3,
        "pcode": "52204",
        "pos": "31",
        "r": 0,
        "s": 1,
        "tb": "B",
        "w": 6,
        "wls": "H"
      },
      {
        "ab": 1,
        "accmEr": 14,
        "accmInn2": 160,
        "bbhp": 0,
        "bf": 4,
        "changeinn": "8.4",
        "er": 0,
        "game": 58,
        "gday": "20240914",
        "gmkey": "20240914KTOB0",
        "hit": 0,
        "hr": 0,
        "inn": "0 ⅓",
        "kk": 0,
        "l": 3,
        "name": "홍건희",
        "pa": 1,
        "pcode": "61643",
        "pos": "41",
        "r": 0,
        "s": 9,
        "tb": "B",
        "w": 4,
        "wls": "H"
      },
      {
        "ab": 3,
        "accmEr": 14,
        "accmInn2": 185,
        "bbhp": 1,
        "bf": 19,
        "changeinn": "8.5",
        "er": 0,
        "game": 57,
        "gday": "20240914",
        "gmkey": "20240914KTOB0",
        "hit": 0,
        "hr": 0,
        "inn": "1 ⅓",
        "kk": 2,
        "l": 2,
        "name": "김택연",
        "pa": 5,
        "pcode": "54263",
        "pos": "51",
        "r": 0,
        "s": 18,
        "tb": "B",
        "w": 3,
        "wls": "S"
      }
    ],
    "schedule": {
      "current": {
        "broadcast": "KBS N SPORTS",
        "cancelFlag": "0",
        "crowdCn": 23750,
        "endFlag": "1",
        "game": "current",
        "gameDate": 20240914,
        "gday": 14,
        "gmkey": "20240914KTOB0",
        "gmonth": 9,
        "gtime": "17:00",
        "gyear": "2024",
        "home": "두산",
        "homeKey": "OB",
        "homeLogo": "http://3.35.51.214/api/static/OB.png",
        "hscore": 2,
        "stadium": "잠실",
        "stadiumKey": "JS",
        "visit": "KT",
        "visitKey": "KT",
        "visitLogo": "http://3.35.51.214/api/static/KT.png",
        "vscore": 1
      },
      "next": {
        "broadcast": "KBS N SPORTS,MBC SPORTS+",
        "cancelFlag": "0",
        "crowdCn": 18700,
        "endFlag": "1",
        "game": "next",
        "gameDate": 20240916,
        "gday": 16,
        "gmkey": "20240916HTKT0",
        "gmonth": 9,
        "gtime": "14:00",
        "gyear": "2024",
        "home": "KT",
        "homeKey": "KT",
        "homeLogo": "http://3.35.51.214/api/static/KT.png",
        "hscore": 5,
        "stadium": "수원",
        "stadiumKey": "SW",
        "visit": "KIA",
        "visitKey": "HT",
        "visitLogo": "http://3.35.51.214/api/static/HT.png",
        "vscore": 11
      },
      "prev": {
        "broadcast": "KBS N SPORTS,SBS SPORTS",
        "cancelFlag": "0",
        "crowdCn": 5962,
        "endFlag": "1",
        "game": "prev",
        "gameDate": 20240912,
        "gday": 12,
        "gmkey": "20240912NCKT0",
        "gmonth": 9,
        "gtime": "18:30",
        "gyear": "2024",
        "home": "KT",
        "homeKey": "KT",
        "homeLogo": "http://3.35.51.214/api/static/KT.png",
        "hscore": 10,
        "stadium": "수원",
        "stadiumKey": "SW",
        "visit": "NC",
        "visitKey": "NC",
        "visitLogo": "http://3.35.51.214/api/static/NC.png",
        "vscore": 4
      }
    },
    "scoreboard": [
      {
        "ballfour": "7",
        "bhome": 0,
        "bhomeName": "KT",
        "error": "1",
        "gameDate": 20240914,
        "hit": "3",
        "run": "1",
        "score1": "1",
        "score10": "-",
        "score11": "-",
        "score12": "-",
        "score2": "0",
        "score3": "0",
        "score4": "0",
        "score5": "0",
        "score6": "0",
        "score7": "0",
        "score8": "0",
        "score9": "0"
      },
      {
        "ballfour": "1",
        "bhome": 1,
        "bhomeName": "두산",
        "error": "1",
        "gameDate": 20240914,
        "hit": "4",
        "run": "2",
        "score1": "0",
        "score10": "-",
        "score11": "-",
        "score12": "-",
        "score2": "1",
        "score3": "1",
        "score4": "0",
        "score5": "0",
        "score6": "0",
        "score7": "0",
        "score8": "0",
        "score9": "-"
      }
    ],
    "vbatters": [
      {
        "ab": 2,
        "accmAb": 535,
        "accmHit": 178,
        "changeinn": "",
        "gday": "20240914",
        "gmkey": "20240914KTOB0",
        "hit": 0,
        "il1": "",
        "il10": "",
        "il11": "",
        "il12": "",
        "il13": "",
        "il14": "",
        "il15": "",
        "il16": "",
        "il17": "",
        "il18": "",
        "il19": "",
        "il2": "",
        "il20": "",
        "il21": "",
        "il22": "",
        "il23": "",
        "il24": "",
        "il25": "",
        "il3": "",
        "il4": "",
        "il5": "",
        "il6": "",
        "il7": "",
        "il8": "",
        "il9": "",
        "inn1": "4구",
        "inn10": "",
        "inn11": "",
        "inn12": "",
        "inn13": "",
        "inn14": "",
        "inn15": "",
        "inn16": "",
        "inn17": "",
        "inn18": "",
        "inn19": "",
        "inn2": "",
        "inn20": "",
        "inn21": "",
        "inn22": "",
        "inn23": "",
        "inn24": "",
        "inn25": "",
        "inn3": "4구",
        "inn4": "",
        "inn5": "삼진",
        "inn6": "",
        "inn7": "삼진",
        "inn8": "",
        "inn9": "",
        "name": "로하스",
        "oneturn": "1",
        "pcode": "67025",
        "position": "우",
        "rbi": 0,
        "run": 1,
        "tb": "T",
        "turn": "11"
      },
      {
        "ab": 3,
        "accmAb": 317,
        "accmHit": 106,
        "changeinn": "",
        "gday": "20240914",
        "gmkey": "20240914KTOB0",
        "hit": 0,
        "il1": "",
        "il10": "",
        "il11": "",
        "il12": "",
        "il13": "",
        "il14": "",
        "il15": "",
        "il16": "",
        "il17": "",
        "il18": "",
        "il19": "",
        "il2": "",
        "il20": "",
        "il21": "",
        "il22": "",
        "il23": "",
        "il24": "",
        "il25": "",
        "il3": "",
        "il4": "",
        "il5": "",
        "il6": "",
        "il7": "",
        "il8": "",
        "il9": "",
        "inn1": "3비",
        "inn10": "",
        "inn11": "",
        "inn12": "",
        "inn13": "",
        "inn14": "",
        "inn15": "",
        "inn16": "",
        "inn17": "",
        "inn18": "",
        "inn19": "",
        "inn2": "",
        "inn20": "",
        "inn21": "",
        "inn22": "",
        "inn23": "",
        "inn24": "",
        "inn25": "",
        "inn3": "투희번",
        "inn4": "",
        "inn5": "중비",
        "inn6": "",
        "inn7": "",
        "inn8": "2땅",
        "inn9": "",
        "name": "김민혁",
        "oneturn": "2",
        "pcode": "64004",
        "position": "좌",
        "rbi": 0,
        "run": 0,
        "tb": "T",
        "turn": "12"
      },
      {
        "ab": 2,
        "accmAb": 387,
        "accmHit": 102,
        "changeinn": "",
        "gday": "20240914",
        "gmkey": "20240914KTOB0",
        "hit": 1,
        "il1": "",
        "il10": "",
        "il11": "",
        "il12": "",
        "il13": "",
        "il14": "",
        "il15": "",
        "il16": "",
        "il17": "",
        "il18": "",
        "il19": "",
        "il2": "",
        "il20": "",
        "il21": "",
        "il22": "",
        "il23": "",
        "il24": "",
        "il25": "",
        "il3": "",
        "il4": "",
        "il5": "",
        "il6": "",
        "il7": "",
        "il8": "",
        "il9": "",
        "inn1": "좌안",
        "inn10": "",
        "inn11": "",
        "inn12": "",
        "inn13": "",
        "inn14": "",
        "inn15": "",
        "inn16": "",
        "inn17": "",
        "inn18": "",
        "inn19": "",
        "inn2": "",
        "inn20": "",
        "inn21": "",
        "inn22": "",
        "inn23": "",
        "inn24": "",
        "inn25": "",
        "inn3": "포파",
        "inn4": "",
        "inn5": "",
        "inn6": "4구",
        "inn7": "",
        "inn8": "4구",
        "inn9": "",
        "name": "장성우",
        "oneturn": "3",
        "pcode": "78548",
        "position": "지",
        "rbi": 0,
        "run": 0,
        "tb": "T",
        "turn": "13"
      },
      {
        "ab": 0,
        "accmAb": 15,
        "accmHit": 3,
        "changeinn": "8",
        "gday": "20240914",
        "gmkey": "20240914KTOB0",
        "hit": 0,
        "il1": "",
        "il10": "",
        "il11": "",
        "il12": "",
        "il13": "",
        "il14": "",
        "il15": "",
        "il16": "",
        "il17": "",
        "il18": "",
        "il19": "",
        "il2": "",
        "il20": "",
        "il21": "",
        "il22": "",
        "il23": "",
        "il24": "",
        "il25": "",
        "il3": "",
        "il4": "",
        "il5": "",
        "il6": "",
        "il7": "",
        "il8": "",
        "il9": "",
        "inn1": "",
        "inn10": "",
        "inn11": "",
        "inn12": "",
        "inn13": "",
        "inn14": "",
        "inn15": "",
        "inn16": "",
        "inn17": "",
        "inn18": "",
        "inn19": "",
        "inn2": "",
        "inn20": "",
        "inn21": "",
        "inn22": "",
        "inn23": "",
        "inn24": "",
        "inn25": "",
        "inn3": "",
        "inn4": "",
        "inn5": "",
        "inn6": "",
        "inn7": "",
        "inn8": "",
        "inn9": "",
        "name": "윤준혁",
        "oneturn": "3",
        "pcode": "50092",
        "position": "주",
        "rbi": 0,
        "run": 0,
        "tb": "T",
        "turn": "23"
      },
      {
        "ab": 2,
        "accmAb": 325,
        "accmHit": 85,
        "changeinn": "",
        "gday": "20240914",
        "gmkey": "20240914KTOB0",
        "hit": 0,
        "il1": "",
        "il10": "",
        "il11": "",
        "il12": "",
        "il13": "",
        "il14": "",
        "il15": "",
        "il16": "",
        "il17": "",
        "il18": "",
        "il19": "",
        "il2": "",
        "il20": "",
        "il21": "",
        "il22": "",
        "il23": "",
        "il24": "",
        "il25": "",
        "il3": "",
        "il4": "",
        "il5": "",
        "il6": "",
        "il7": "",
        "il8": "",
        "il9": "",
        "inn1": "4구",
        "inn10": "",
        "inn11": "",
        "inn12": "",
        "inn13": "",
        "inn14": "",
        "inn15": "",
        "inn16": "",
        "inn17": "",
        "inn18": "",
        "inn19": "",
        "inn2": "",
        "inn20": "",
        "inn21": "",
        "inn22": "",
        "inn23": "",
        "inn24": "",
        "inn25": "",
        "inn3": "유땅",
        "inn4": "",
        "inn5": "",
        "inn6": "4구",
        "inn7": "",
        "inn8": "투땅",
        "inn9": "",
        "name": "문상철",
        "oneturn": "4",
        "pcode": "64007",
        "position": "一",
        "rbi": 0,
        "run": 0,
        "tb": "T",
        "turn": "14"
      },
      {
        "ab": 4,
        "accmAb": 461,
        "accmHit": 121,
        "changeinn": "",
        "gday": "20240914",
        "gmkey": "20240914KTOB0",
        "hit": 0,
        "il1": "",
        "il10": "",
        "il11": "",
        "il12": "",
        "il13": "",
        "il14": "",
        "il15": "",
        "il16": "",
        "il17": "",
        "il18": "",
        "il19": "",
        "il2": "",
        "il20": "",
        "il21": "",
        "il22": "",
        "il23": "",
        "il24": "",
        "il25": "",
        "il3": "",
        "il4": "",
        "il5": "",
        "il6": "",
        "il7": "",
        "il8": "",
        "il9": "",
        "inn1": "삼진",
        "inn10": "",
        "inn11": "",
        "inn12": "",
        "inn13": "",
        "inn14": "",
        "inn15": "",
        "inn16": "",
        "inn17": "",
        "inn18": "",
        "inn19": "",
        "inn2": "",
        "inn20": "",
        "inn21": "",
        "inn22": "",
        "inn23": "",
        "inn24": "",
        "inn25": "",
        "inn3": "",
        "inn4": "삼진",
        "inn5": "",
        "inn6": "유병",
        "inn7": "",
        "inn8": "삼진",
        "inn9": "",
        "name": "황재균",
        "oneturn": "5",
        "pcode": "76313",
        "position": "三",
        "rbi": 0,
        "run": 0,
        "tb": "T",
        "turn": "15"
      },
      {
        "ab": 3,
        "accmAb": 357,
        "accmHit": 100,
        "changeinn": "",
        "gday": "20240914",
        "gmkey": "20240914KTOB0",
        "hit": 1,
        "il1": "",
        "il10": "",
        "il11": "",
        "il12": "",
        "il13": "",
        "il14": "",
        "il15": "",
        "il16": "",
        "il17": "",
        "il18": "",
        "il19": "",
        "il2": "",
        "il20": "",
        "il21": "",
        "il22": "",
        "il23": "",
        "il24": "",
        "il25": "",
        "il3": "",
        "il4": "",
        "il5": "",
        "il6": "",
        "il7": "",
        "il8": "",
        "il9": "",
        "inn1": "중비",
        "inn10": "",
        "inn11": "",
        "inn12": "",
        "inn13": "",
        "inn14": "",
        "inn15": "",
        "inn16": "",
        "inn17": "",
        "inn18": "",
        "inn19": "",
        "inn2": "",
        "inn20": "",
        "inn21": "",
        "inn22": "",
        "inn23": "",
        "inn24": "",
        "inn25": "",
        "inn3": "",
        "inn4": "좌2",
        "inn5": "",
        "inn6": "3땅",
        "inn7": "",
        "inn8": "",
        "inn9": "4구",
        "name": "김상수",
        "oneturn": "6",
        "pcode": "79402",
        "position": "二",
        "rbi": 0,
        "run": 0,
        "tb": "T",
        "turn": "16"
      },
      {
        "ab": 3,
        "accmAb": 373,
        "accmHit": 99,
        "changeinn": "",
        "gday": "20240914",
        "gmkey": "20240914KTOB0",
        "hit": 0,
        "il1": "",
        "il10": "",
        "il11": "",
        "il12": "",
        "il13": "",
        "il14": "",
        "il15": "",
        "il16": "",
        "il17": "",
        "il18": "",
        "il19": "",
        "il2": "",
        "il20": "",
        "il21": "",
        "il22": "",
        "il23": "",
        "il24": "",
        "il25": "",
        "il3": "",
        "il4": "",
        "il5": "",
        "il6": "",
        "il7": "",
        "il8": "",
        "il9": "",
        "inn1": "",
        "inn10": "",
        "inn11": "",
        "inn12": "",
        "inn13": "",
        "inn14": "",
        "inn15": "",
        "inn16": "",
        "inn17": "",
        "inn18": "",
        "inn19": "",
        "inn2": "삼진",
        "inn20": "",
        "inn21": "",
        "inn22": "",
        "inn23": "",
        "inn24": "",
        "inn25": "",
        "inn3": "",
        "inn4": "삼진",
        "inn5": "",
        "inn6": "",
        "inn7": "유땅",
        "inn8": "",
        "inn9": "",
        "name": "배정대",
        "oneturn": "7",
        "pcode": "64166",
        "position": "중",
        "rbi": 0,
        "run": 0,
        "tb": "T",
        "turn": "17"
      },
      {
        "ab": 0,
        "accmAb": 13,
        "accmHit": 3,
        "changeinn": "9",
        "gday": "20240914",
        "gmkey": "20240914KTOB0",
        "hit": 0,
        "il1": "",
        "il10": "",
        "il11": "",
        "il12": "",
        "il13": "",
        "il14": "",
        "il15": "",
        "il16": "",
        "il17": "",
        "il18": "",
        "il19": "",
        "il2": "",
        "il20": "",
        "il21": "",
        "il22": "",
        "il23": "",
        "il24": "",
        "il25": "",
        "il3": "",
        "il4": "",
        "il5": "",
        "il6": "",
        "il7": "",
        "il8": "",
        "il9": "",
        "inn1": "",
        "inn10": "",
        "inn11": "",
        "inn12": "",
        "inn13": "",
        "inn14": "",
        "inn15": "",
        "inn16": "",
        "inn17": "",
        "inn18": "",
        "inn19": "",
        "inn2": "",
        "inn20": "",
        "inn21": "",
        "inn22": "",
        "inn23": "",
        "inn24": "",
        "inn25": "",
        "inn3": "",
        "inn4": "",
        "inn5": "",
        "inn6": "",
        "inn7": "",
        "inn8": "",
        "inn9": "투희번",
        "name": "송민섭",
        "oneturn": "7",
        "pcode": "64012",
        "position": "타",
        "rbi": 0,
        "run": 0,
        "tb": "T",
        "turn": "27"
      },
      {
        "ab": 3,
        "accmAb": 141,
        "accmHit": 34,
        "changeinn": "",
        "gday": "20240914",
        "gmkey": "20240914KTOB0",
        "hit": 0,
        "il1": "",
        "il10": "",
        "il11": "",
        "il12": "",
        "il13": "",
        "il14": "",
        "il15": "",
        "il16": "",
        "il17": "",
        "il18": "",
        "il19": "",
        "il2": "",
        "il20": "",
        "il21": "",
        "il22": "",
        "il23": "",
        "il24": "",
        "il25": "",
        "il3": "",
        "il4": "",
        "il5": "",
        "il6": "",
        "il7": "",
        "il8": "",
        "il9": "",
        "inn1": "",
        "inn10": "",
        "inn11": "",
        "inn12": "",
        "inn13": "",
        "inn14": "",
        "inn15": "",
        "inn16": "",
        "inn17": "",
        "inn18": "",
        "inn19": "",
        "inn2": "중비",
        "inn20": "",
        "inn21": "",
        "inn22": "",
        "inn23": "",
        "inn24": "",
        "inn25": "",
        "inn3": "",
        "inn4": "유땅",
        "inn5": "",
        "inn6": "",
        "inn7": "3땅",
        "inn8": "",
        "inn9": "",
        "name": "심우준",
        "oneturn": "8",
        "pcode": "64006",
        "position": "유",
        "rbi": 0,
        "run": 0,
        "tb": "T",
        "turn": "18"
      },
      {
        "ab": 1,
        "accmAb": 520,
        "accmHit": 150,
        "changeinn": "9",
        "gday": "20240914",
        "gmkey": "20240914KTOB0",
        "hit": 0,
        "il1": "",
        "il10": "",
        "il11": "",
        "il12": "",
        "il13": "",
        "il14": "",
        "il15": "",
        "il16": "",
        "il17": "",
        "il18": "",
        "il19": "",
        "il2": "",
        "il20": "",
        "il21": "",
        "il22": "",
        "il23": "",
        "il24": "",
        "il25": "",
        "il3": "",
        "il4": "",
        "il5": "",
        "il6": "",
        "il7": "",
        "il8": "",
        "il9": "",
        "inn1": "",
        "inn10": "",
        "inn11": "",
        "inn12": "",
        "inn13": "",
        "inn14": "",
        "inn15": "",
        "inn16": "",
        "inn17": "",
        "inn18": "",
        "inn19": "",
        "inn2": "",
        "inn20": "",
        "inn21": "",
        "inn22": "",
        "inn23": "",
        "inn24": "",
        "inn25": "",
        "inn3": "",
        "inn4": "",
        "inn5": "",
        "inn6": "",
        "inn7": "",
        "inn8": "",
        "inn9": "삼진",
        "name": "강백호",
        "oneturn": "8",
        "pcode": "68050",
        "position": "타",
        "rbi": 0,
        "run": 0,
        "tb": "T",
        "turn": "28"
      },
      {
        "ab": 3,
        "accmAb": 34,
        "accmHit": 11,
        "changeinn": "",
        "gday": "20240914",
        "gmkey": "20240914KTOB0",
        "hit": 1,
        "il1": "",
        "il10": "",
        "il11": "",
        "il12": "",
        "il13": "",
        "il14": "",
        "il15": "",
        "il16": "",
        "il17": "",
        "il18": "",
        "il19": "",
        "il2": "",
        "il20": "",
        "il21": "",
        "il22": "",
        "il23": "",
        "il24": "",
        "il25": "",
        "il3": "",
        "il4": "",
        "il5": "",
        "il6": "",
        "il7": "",
        "il8": "",
        "il9": "",
        "inn1": "",
        "inn10": "",
        "inn11": "",
        "inn12": "",
        "inn13": "",
        "inn14": "",
        "inn15": "",
        "inn16": "",
        "inn17": "",
        "inn18": "",
        "inn19": "",
        "inn2": "좌비",
        "inn20": "",
        "inn21": "",
        "inn22": "",
        "inn23": "",
        "inn24": "",
        "inn25": "",
        "inn3": "",
        "inn4": "",
        "inn5": "2비",
        "inn6": "",
        "inn7": "중안",
        "inn8": "",
        "inn9": "",
        "name": "조대현",
        "oneturn": "9",
        "pcode": "68089",
        "position": "포",
        "rbi": 0,
        "run": 0,
        "tb": "T",
        "turn": "19"
      },
      {
        "ab": 1,
        "accmAb": 271,
        "accmHit": 63,
        "changeinn": "9",
        "gday": "20240914",
        "gmkey": "20240914KTOB0",
        "hit": 0,
        "il1": "",
        "il10": "",
        "il11": "",
        "il12": "",
        "il13": "",
        "il14": "",
        "il15": "",
        "il16": "",
        "il17": "",
        "il18": "",
        "il19": "",
        "il2": "",
        "il20": "",
        "il21": "",
        "il22": "",
        "il23": "",
        "il24": "",
        "il25": "",
        "il3": "",
        "il4": "",
        "il5": "",
        "il6": "",
        "il7": "",
        "il8": "",
        "il9": "",
        "inn1": "",
        "inn10": "",
        "inn11": "",
        "inn12": "",
        "inn13": "",
        "inn14": "",
        "inn15": "",
        "inn16": "",
        "inn17": "",
        "inn18": "",
        "inn19": "",
        "inn2": "",
        "inn20": "",
        "inn21": "",
        "inn22": "",
        "inn23": "",
        "inn24": "",
        "inn25": "",
        "inn3": "",
        "inn4": "",
        "inn5": "",
        "inn6": "",
        "inn7": "",
        "inn8": "",
        "inn9": "유비",
        "name": "오재일",
        "oneturn": "9",
        "pcode": "75334",
        "position": "타",
        "rbi": 0,
        "run": 0,
        "tb": "T",
        "turn": "29"
      },
      {
        "ab": 27,
        "accmAb": 0,
        "accmHit": 0,
        "changeinn": "",
        "gday": "20240914",
        "gmkey": "20240914KTOB0",
        "hit": 3,
        "il1": "",
        "il10": "",
        "il11": "",
        "il12": "",
        "il13": "",
        "il14": "",
        "il15": "",
        "il16": "",
        "il17": "",
        "il18": "",
        "il19": "",
        "il2": "",
        "il20": "",
        "il21": "",
        "il22": "",
        "il23": "",
        "il24": "",
        "il25": "",
        "il3": "",
        "il4": "",
        "il5": "",
        "il6": "",
        "il7": "",
        "il8": "",
        "il9": "",
        "inn1": "",
        "inn10": "",
        "inn11": "",
        "inn12": "",
        "inn13": "",
        "inn14": "",
        "inn15": "",
        "inn16": "",
        "inn17": "",
        "inn18": "",
        "inn19": "",
        "inn2": "",
        "inn20": "",
        "inn21": "",
        "inn22": "",
        "inn23": "",
        "inn24": "",
        "inn25": "",
        "inn3": "",
        "inn4": "",
        "inn5": "",
        "inn6": "",
        "inn7": "",
        "inn8": "",
        "inn9": "",
        "name": "합계",
        "oneturn": "",
        "pcode": "T",
        "position": "",
        "rbi": 0,
        "run": 1,
        "tb": "T",
        "turn": ""
      }
    ],
    "vpitchers": [
      {
        "ab": 19,
        "accmEr": 52,
        "accmInn2": 267,
        "bbhp": 1,
        "bf": 86,
        "changeinn": "",
        "er": 1,
        "game": 16,
        "gday": "20240914",
        "gmkey": "20240914KTOB0",
        "hit": 4,
        "hr": 0,
        "inn": "6",
        "kk": 4,
        "l": 7,
        "name": "고영표",
        "pa": 22,
        "pcode": "64001",
        "pos": "11",
        "r": 2,
        "s": 0,
        "tb": "T",
        "w": 5,
        "wls": "L"
      },
      {
        "ab": 6,
        "accmEr": 25,
        "accmInn2": 120,
        "bbhp": 0,
        "bf": 22,
        "changeinn": "7.5",
        "er": 0,
        "game": 36,
        "gday": "20240914",
        "gmkey": "20240914KTOB0",
        "hit": 0,
        "hr": 0,
        "inn": "2",
        "kk": 0,
        "l": 1,
        "name": "손동현",
        "pa": 6,
        "pcode": "69041",
        "pos": "21",
        "r": 0,
        "s": 1,
        "tb": "T",
        "w": 1,
        "wls": ""
      }
    ]
  }
}