{
  "data": {
    "list": [
      {
        "date": "20240923",
        "rank": 6
      },
      {
        "date": "20240924",
        "rank": 5
      },
      {
        "date": "20240925",
        "rank": 5
      },
      {
        "date": "20240926",
        "rank": 5
      },
      {
        "date": "20240927",
        "rank": 5
      },
      {
        "date": "20240928",
        "rank": 5
      },
      {
        "date": "20240929",
        "rank": 5
      },
      {
        "date": "20240930",
        "rank": 5
      },
      {
        "date": "20241001",
        "rank": 5
      },
      {
        "date": "20241002",
        "rank": 5
      },
      {
        "date": "20241003",
        "rank": 5
      },
      {
        "date": "20241004",
        "rank": 5
      },
      {
        "date": "20241005",
        "rank": 5
      },
      {
        "date": "20241006",
        "rank": 5
      },
      {
        "date": "20241007",
        "rank": 5
      },
      {
        "date": "20241008",
        "rank": 5
      },
      {
        "date": "20241009",
        "rank": 5
      },
      {
        "date": "20241010",
        "rank": 5
      },
      {
        "date": "20241011",
        "rank": 5
      },
      {
        "date": "20241012",
        "rank": 5
      },
      {
        "date": "20241013",
        "rank": 5
      },
      {
        "date": "20241014",
        "rank": 5
      },
      {
        "date": "20241015",
        "rank": 5
      },
      {
        "date": "20241016",
        "rank": 5
      },
      {
        "date": "20241017",
        "rank": 5
      },
      {
        "date": "20241018",
        "rank": 5
      },
      {
        "date": "20241019",
        "rank": 5
      },
      {
        "date": "20241020",
        "rank": 5
      },
      {
        "date": "20241021",
        "rank": 5
      },
      {
        "date": "20241022",
        "rank": 5
      },
      {
        "date": "20241023",
        "rank": 5
      }
    ]
  }
}