{
  "data": {
    "list": [
      {
        "ab": 3,
        "babip": "1",
        "bb": 0,
        "bbhp": 0,
        "bbkk": "0",
        "bra": "0.333",
        "cba": "0",
        "cgopo": "0",
        "cs": 0,
        "fl": 0,
        "gamenum": 2,
        "gd": 0,
        "gofo": "0",
        "gr": 0,
        "gyear": "2022",
        "h1": 0,
        "h2": 1,
        "h3": 0,
        "hit": 1,
        "hp": 0,
        "hr": 0,
        "hra": "0.333",
        "hrab": 0,
        "ib": 0,
        "iso": "0.333",
        "kk": 2,
        "kkab": 0,
        "lba": "1",
        "lgopo": "0",
        "nppa": 3,
        "ops": "1",
        "opsPlus": "178.776",
        "pa": 3,
        "paFlag": "0",
        "pcode": "50007",
        "playerName": "문상준",
        "playerPrvwImg": "https://wizzap.ktwiz.co.kr/files/playerImg/ktImg/50007_2023-03-20_100932.jpg",
        "po": 0,
        "rba": "0",
        "rbi": 0,
        "rgopo": "0",
        "run": 0,
        "sb": 0,
        "sbTryCn": 0,
        "sba": "0",
        "sf": 0,
        "sh": 0,
        "slab": 0,
        "slg": "0.667",
        "spHra": "1",
        "startCn": 0,
        "subCn": 2,
        "teamName": "KT",
        "wrHit": "0"
      },
      {
        "ab": 3,
        "babip": "0.333333",
        "bb": 0,
        "bbhp": 0,
        "bbkk": "0",
        "bra": "0.333",
        "cba": "0.333",
        "cgopo": "0",
        "cs": 0,
        "fl": 2,
        "gamenum": 4,
        "gd": 0,
        "gofo": "0",
        "gr": 0,
        "gyear": "2022",
        "h1": 1,
        "h2": 0,
        "h3": 0,
        "hit": 1,
        "hp": 0,
        "hr": 0,
        "hra": "0.333",
        "hrab": 0,
        "ib": 0,
        "iso": "0",
        "kk": 0,
        "kkab": 0,
        "lba": "0.333",
        "lgopo": "0",
        "nppa": 3,
        "ops": "0.667",
        "opsPlus": "89.7091",
        "pa": 3,
        "paFlag": "0",
        "pcode": "51009",
        "playerName": "전진영",
        "playerPrvwImg": "https://wizzap.ktwiz.co.kr/files/playerImg/ktImg/51009_2022-02-23_132305.jpg",
        "po": 0,
        "rba": "0.333",
        "rbi": 1,
        "rgopo": "0",
        "run": 0,
        "sb": 0,
        "sbTryCn": 0,
        "sba": "0",
        "sf": 0,
        "sh": 0,
        "slab": 0,
        "slg": "0.333",
        "spHra": "0.5",
        "startCn": 0,
        "subCn": 4,
        "teamName": "KT",
        "wrHit": "0"
      },
      {
        "ab": 474,
        "babip": "0.3575",
        "bb": 49,
        "bbhp": 52,
        "bbkk": "0.66",
        "bra": "0.374",
        "cba": "0.247",
        "cgopo": "0.33",
        "cs": 4,
        "fl": 123,
        "gamenum": 131,
        "gd": 3,
        "gofo": "1.09",
        "gr": 134,
        "gyear": "2022",
        "h1": 121,
        "h2": 18,
        "h3": 4,
        "hit": 146,
        "hp": 3,
        "hr": 3,
        "hra": "0.308",
        "hrab": 0,
        "ib": 3,
        "iso": "0.074",
        "kk": 74,
        "kkab": 0,
        "lba": "0.39",
        "lgopo": "0.64",
        "nppa": 4,
        "ops": "0.756",
        "opsPlus": "115.2",
        "pa": 531,
        "paFlag": "1",
        "pcode": "64868",
        "playerName": "조용호",
        "playerPrvwImg": "https://wizzap.ktwiz.co.kr/files/playerImg/ktImg/64868_2024-03-06_135854.jpg",
        "po": 0,
        "rba": "0.364",
        "rbi": 44,
        "rgopo": "3.38",
        "run": 52,
        "sb": 5,
        "sbTryCn": 9,
        "sba": "0.556",
        "sf": 3,
        "sh": 2,
        "slab": 0,
        "slg": "0.382",
        "spHra": "0.293",
        "startCn": 123,
        "subCn": 8,
        "teamName": "KT",
        "wrHit": "9"
      },
      {
        "ab": 283,
        "babip": "0.36612",
        "bb": 33,
        "bbhp": 36,
        "bbkk": "0.37",
        "bra": "0.362",
        "cba": "0.269",
        "cgopo": "0.14",
        "cs": 1,
        "fl": 71,
        "gamenum": 80,
        "gd": 3,
        "gofo": "0.63",
        "gr": 45,
        "gyear": "2022",
        "h1": 47,
        "h2": 19,
        "h3": 1,
        "hit": 81,
        "hp": 3,
        "hr": 14,
        "hra": "0.286",
        "hrab": 0,
        "ib": 3,
        "iso": "0.223",
        "kk": 90,
        "kkab": 0,
        "lba": "0.484",
        "lgopo": "1.35",
        "nppa": 4,
        "ops": "0.871",
        "opsPlus": "145.43",
        "pa": 323,
        "paFlag": "0",
        "pcode": "52009",
        "playerName": "알포드",
        "playerPrvwImg": "https://wizzap.ktwiz.co.kr/files/playerImg/ktImg/52009_2023-03-20_102226.jpg",
        "po": 0,
        "rba": "0.247",
        "rbi": 50,
        "rgopo": "0.42",
        "run": 48,
        "sb": 5,
        "sbTryCn": 6,
        "sba": "0.833",
        "sf": 4,
        "sh": 0,
        "slab": 0,
        "slg": "0.509",
        "spHra": "0.239",
        "startCn": 77,
        "subCn": 3,
        "teamName": "KT",
        "wrHit": "9"
      },
      {
        "ab": 373,
        "babip": "0.33758",
        "bb": 37,
        "bbhp": 39,
        "bbkk": "0.6",
        "bra": "0.349",
        "cba": "0.255",
        "cgopo": "0.5",
        "cs": 9,
        "fl": 87,
        "gamenum": 132,
        "gd": 10,
        "gofo": "1.39",
        "gr": 121,
        "gyear": "2022",
        "h1": 94,
        "h2": 10,
        "h3": 2,
        "hit": 106,
        "hp": 2,
        "hr": 0,
        "hra": "0.284",
        "hrab": 0,
        "ib": 2,
        "iso": "0.038",
        "kk": 62,
        "kkab": 0,
        "lba": "0.376",
        "lgopo": "0.58",
        "nppa": 3,
        "ops": "0.671",
        "opsPlus": "91.6242",
        "pa": 434,
        "paFlag": "0",
        "pcode": "64004",
        "playerName": "김민혁",
        "playerPrvwImg": "https://wizzap.ktwiz.co.kr/files/playerImg/ktImg/64004_2024-03-06_134725.jpg",
        "po": 0,
        "rba": "0.369",
        "rbi": 35,
        "rgopo": "7.18",
        "run": 47,
        "sb": 6,
        "sbTryCn": 15,
        "sba": "0.4",
        "sf": 3,
        "sh": 19,
        "slab": 0,
        "slg": "0.322",
        "spHra": "0.279",
        "startCn": 98,
        "subCn": 34,
        "teamName": "KT",
        "wrHit": "5"
      },
      {
        "ab": 429,
        "babip": "0.30855",
        "bb": 40,
        "bbhp": 52,
        "bbkk": "0.31",
        "bra": "0.349",
        "cba": "0.287",
        "cgopo": "0.15",
        "cs": 3,
        "fl": 111,
        "gamenum": 124,
        "gd": 7,
        "gofo": "0.68",
        "gr": 75,
        "gyear": "2022",
        "h1": 66,
        "h2": 17,
        "h3": 0,
        "hit": 118,
        "hp": 12,
        "hr": 35,
        "hra": "0.275",
        "hrab": 0,
        "ib": 3,
        "iso": "0.284",
        "kk": 131,
        "kkab": 0,
        "lba": "0.512",
        "lgopo": "2.03",
        "nppa": 4,
        "ops": "0.909",
        "opsPlus": "154.824",
        "pa": 487,
        "paFlag": "1",
        "pcode": "75125",
        "playerName": "박병호",
        "playerPrvwImg": "https://wizzap.ktwiz.co.kr/files/playerImg/otherImg/75125_2024-07-10_155556.jpg",
        "po": 0,
        "rba": "0.201",
        "rbi": 98,
        "rgopo": "0.2",
        "run": 72,
        "sb": 5,
        "sbTryCn": 8,
        "sba": "0.625",
        "sf": 6,
        "sh": 0,
        "slab": 0,
        "slg": "0.559",
        "spHra": "0.259",
        "startCn": 115,
        "subCn": 9,
        "teamName": "KT",
        "wrHit": "11"
      },
      {
        "ab": 231,
        "babip": "0.385621",
        "bb": 33,
        "bbhp": 33,
        "bbkk": "0.43",
        "bra": "0.360",
        "cba": "0.243",
        "cgopo": "0.27",
        "cs": 0,
        "fl": 48,
        "gamenum": 98,
        "gd": 4,
        "gofo": "0.96",
        "gr": 46,
        "gyear": "2022",
        "h1": 42,
        "h2": 16,
        "h3": 1,
        "hit": 63,
        "hp": 0,
        "hr": 4,
        "hra": "0.273",
        "hrab": 0,
        "ib": 1,
        "iso": "0.13",
        "kk": 77,
        "kkab": 0,
        "lba": "0.283",
        "lgopo": "0.41",
        "nppa": 4,
        "ops": "0.762",
        "opsPlus": "116.558",
        "pa": 270,
        "paFlag": "0",
        "pcode": "62558",
        "playerName": "김준태",
        "playerPrvwImg": "https://wizzap.ktwiz.co.kr/files/playerImg/ktImg/62558_2024-03-06_130605.jpg",
        "po": 0,
        "rba": "0.474",
        "rbi": 27,
        "rgopo": "2.19",
        "run": 28,
        "sb": 2,
        "sbTryCn": 2,
        "sba": "1",
        "sf": 3,
        "sh": 3,
        "slab": 0,
        "slg": "0.403",
        "spHra": "0.25",
        "startCn": 64,
        "subCn": 34,
        "teamName": "KT",
        "wrHit": "0"
      },
      {
        "ab": 508,
        "babip": "0.339474",
        "bb": 54,
        "bbhp": 58,
        "bbkk": "0.43",
        "bra": "0.339",
        "cba": "0.23",
        "cgopo": "0.42",
        "cs": 4,
        "fl": 134,
        "gamenum": 144,
        "gd": 2,
        "gofo": "0.87",
        "gr": 117,
        "gyear": "2022",
        "h1": 103,
        "h2": 24,
        "h3": 2,
        "hit": 135,
        "hp": 4,
        "hr": 6,
        "hra": "0.266",
        "hrab": 0,
        "ib": 0,
        "iso": "0.091",
        "kk": 126,
        "kkab": 0,
        "lba": "0.474",
        "lgopo": "2.58",
        "nppa": 4,
        "ops": "0.695",
        "opsPlus": "97.6606",
        "pa": 575,
        "paFlag": "1",
        "pcode": "64166",
        "playerName": "배정대",
        "playerPrvwImg": "https://wizzap.ktwiz.co.kr/files/playerImg/ktImg/64166_2024-03-06_135300.jpg",
        "po": 0,
        "rba": "0.296",
        "rbi": 56,
        "rgopo": "0.33",
        "run": 64,
        "sb": 19,
        "sbTryCn": 23,
        "sba": "0.826",
        "sf": 4,
        "sh": 5,
        "slab": 0,
        "slg": "0.356",
        "spHra": "0.281",
        "startCn": 134,
        "subCn": 10,
        "teamName": "KT",
        "wrHit": "9"
      },
      {
        "ab": 519,
        "babip": "0.305825",
        "bb": 53,
        "bbhp": 58,
        "bbkk": "0.54",
        "bra": "0.335",
        "cba": "0.28",
        "cgopo": "0.16",
        "cs": 3,
        "fl": 154,
        "gamenum": 141,
        "gd": 17,
        "gofo": "0.86",
        "gr": 132,
        "gyear": "2022",
        "h1": 98,
        "h2": 25,
        "h3": 3,
        "hit": 136,
        "hp": 5,
        "hr": 10,
        "hra": "0.262",
        "hrab": 0,
        "ib": 5,
        "iso": "0.118",
        "kk": 99,
        "kkab": 0,
        "lba": "0.453",
        "lgopo": "2.2",
        "nppa": 3,
        "ops": "0.715",
        "opsPlus": "102.848",
        "pa": 581,
        "paFlag": "1",
        "pcode": "76313",
        "playerName": "황재균",
        "playerPrvwImg": "https://wizzap.ktwiz.co.kr/files/playerImg/ktImg/76313_2024-03-06_133910.jpg",
        "po": 1,
        "rba": "0.268",
        "rbi": 64,
        "rgopo": "0.57",
        "run": 59,
        "sb": 6,
        "sbTryCn": 9,
        "sba": "0.667",
        "sf": 2,
        "sh": 2,
        "slab": 0,
        "slg": "0.380",
        "spHra": "0.303",
        "startCn": 136,
        "subCn": 5,
        "teamName": "KT",
        "wrHit": "4"
      },
      {
        "ab": 362,
        "babip": "0.283582",
        "bb": 52,
        "bbhp": 54,
        "bbkk": "0.66",
        "bra": "0.353",
        "cba": "0.269",
        "cgopo": "0.3",
        "cs": 0,
        "fl": 109,
        "gamenum": 117,
        "gd": 12,
        "gofo": "0.76",
        "gr": 83,
        "gyear": "2022",
        "h1": 65,
        "h2": 11,
        "h3": 0,
        "hit": 94,
        "hp": 2,
        "hr": 18,
        "hra": "0.260",
        "hrab": 0,
        "ib": 2,
        "iso": "0.18",
        "kk": 79,
        "kkab": 0,
        "lba": "0.452",
        "lgopo": "3.32",
        "nppa": 4,
        "ops": "0.792",
        "opsPlus": "124.036",
        "pa": 420,
        "paFlag": "0",
        "pcode": "78548",
        "playerName": "장성우",
        "playerPrvwImg": "https://wizzap.ktwiz.co.kr/files/playerImg/ktImg/78548_2024-03-06_130913.jpg",
        "po": 3,
        "rba": "0.279",
        "rbi": 55,
        "rgopo": "0.17",
        "run": 48,
        "sb": 1,
        "sbTryCn": 1,
        "sba": "1",
        "sf": 3,
        "sh": 1,
        "slab": 0,
        "slg": "0.439",
        "spHra": "0.277",
        "startCn": 98,
        "subCn": 19,
        "teamName": "KT",
        "wrHit": "10"
      },
      {
        "ab": 72,
        "babip": "0.288462",
        "bb": 4,
        "bbhp": 6,
        "bbkk": "0.22",
        "bra": "0.304",
        "cba": "0.192",
        "cgopo": "0.5",
        "cs": 0,
        "fl": 20,
        "gamenum": 18,
        "gd": 2,
        "gofo": "0.85",
        "gr": 17,
        "gyear": "2022",
        "h1": 13,
        "h2": 1,
        "h3": 1,
        "hit": 18,
        "hp": 2,
        "hr": 3,
        "hra": "0.250",
        "hrab": 0,
        "ib": 0,
        "iso": "0.167",
        "kk": 18,
        "kkab": 0,
        "lba": "0.346",
        "lgopo": "0.56",
        "nppa": 3,
        "ops": "0.72",
        "opsPlus": "103.321",
        "pa": 80,
        "paFlag": "0",
        "pcode": "52025",
        "playerName": "라모스",
        "playerPrvwImg": "https://wizzap.ktwiz.co.kr/files/playerImg/ktImg/52025_2022-02-23_160752.jpg",
        "po": 0,
        "rba": "0.462",
        "rbi": 11,
        "rgopo": "1.43",
        "run": 10,
        "sb": 2,
        "sbTryCn": 2,
        "sba": "1",
        "sf": 1,
        "sh": 1,
        "slab": 0,
        "slg": "0.417",
        "spHra": "0.1",
        "startCn": 18,
        "subCn": 0,
        "teamName": "KT",
        "wrHit": "1"
      },
      {
        "ab": 57,
        "babip": "0.297297",
        "bb": 3,
        "bbhp": 3,
        "bbkk": "0.18",
        "bra": "0.283",
        "cba": "0.268",
        "cgopo": "0.67",
        "cs": 0,
        "fl": 11,
        "gamenum": 35,
        "gd": 5,
        "gofo": "1.36",
        "gr": 15,
        "gyear": "2022",
        "h1": 9,
        "h2": 2,
        "h3": 0,
        "hit": 14,
        "hp": 0,
        "hr": 3,
        "hra": "0.246",
        "hrab": 0,
        "ib": 0,
        "iso": "0.193",
        "kk": 17,
        "kkab": 0,
        "lba": "0.463",
        "lgopo": "2.5",
        "nppa": 3,
        "ops": "0.722",
        "opsPlus": "102.824",
        "pa": 63,
        "paFlag": "0",
        "pcode": "64115",
        "playerName": "장준원",
        "playerPrvwImg": "https://wizzap.ktwiz.co.kr/files/playerImg/ktImg/64115_2024-03-06_133612.jpg",
        "po": 0,
        "rba": "0.268",
        "rbi": 10,
        "rgopo": "0.75",
        "run": 7,
        "sb": 1,
        "sbTryCn": 1,
        "sba": "1",
        "sf": 0,
        "sh": 3,
        "slab": 0,
        "slg": "0.439",
        "spHra": "0.364",
        "startCn": 13,
        "subCn": 22,
        "teamName": "KT",
        "wrHit": "0"
      },
      {
        "ab": 237,
        "babip": "0.275132",
        "bb": 23,
        "bbhp": 24,
        "bbkk": "0.52",
        "bra": "0.312",
        "cba": "0.204",
        "cgopo": "0.31",
        "cs": 0,
        "fl": 71,
        "gamenum": 62,
        "gd": 6,
        "gofo": "0.93",
        "gr": 66,
        "gyear": "2022",
        "h1": 40,
        "h2": 12,
        "h3": 0,
        "hit": 58,
        "hp": 1,
        "hr": 6,
        "hra": "0.245",
        "hrab": 0,
        "ib": 2,
        "iso": "0.127",
        "kk": 44,
        "kkab": 0,
        "lba": "0.414",
        "lgopo": "0.6",
        "nppa": 4,
        "ops": "0.683",
        "opsPlus": "93.4788",
        "pa": 264,
        "paFlag": "0",
        "pcode": "68050",
        "playerName": "강백호",
        "playerPrvwImg": "https://wizzap.ktwiz.co.kr/files/playerImg/ktImg/68050_2024-03-06_175901.jpg",
        "po": 1,
        "rba": "0.382",
        "rbi": 29,
        "rgopo": "2.47",
        "run": 24,
        "sb": 0,
        "sbTryCn": 0,
        "sba": "0",
        "sf": 2,
        "sh": 1,
        "slab": 0,
        "slg": "0.371",
        "spHra": "0.23",
        "startCn": 60,
        "subCn": 2,
        "teamName": "KT",
        "wrHit": "4"
      },
      {
        "ab": 388,
        "babip": "0.284345",
        "bb": 43,
        "bbhp": 45,
        "bbkk": "0.57",
        "bra": "0.316",
        "cba": "0.193",
        "cgopo": "0.38",
        "cs": 2,
        "fl": 120,
        "gamenum": 132,
        "gd": 11,
        "gofo": "0.87",
        "gr": 104,
        "gyear": "2022",
        "h1": 79,
        "h2": 8,
        "h3": 2,
        "hit": 93,
        "hp": 2,
        "hr": 4,
        "hra": "0.240",
        "hrab": 0,
        "ib": 0,
        "iso": "0.062",
        "kk": 75,
        "kkab": 0,
        "lba": "0.516",
        "lgopo": "1.57",
        "nppa": 4,
        "ops": "0.617",
        "opsPlus": "76.2909",
        "pa": 449,
        "paFlag": "1",
        "pcode": "64006",
        "playerName": "심우준",
        "playerPrvwImg": "https://wizzap.ktwiz.co.kr/files/playerImg/ktImg/64006_2024-07-23_111000.jpg",
        "po": 1,
        "rba": "0.291",
        "rbi": 34,
        "rgopo": "0.46",
        "run": 69,
        "sb": 23,
        "sbTryCn": 25,
        "sba": "0.92",
        "sf": 4,
        "sh": 11,
        "slab": 0,
        "slg": "0.302",
        "spHra": "0.175",
        "startCn": 124,
        "subCn": 8,
        "teamName": "KT",
        "wrHit": "4"
      },
      {
        "ab": 76,
        "babip": "0.36",
        "bb": 10,
        "bbhp": 10,
        "bbkk": "0.38",
        "bra": "0.326",
        "cba": "0.34",
        "cgopo": "4",
        "cs": 0,
        "fl": 8,
        "gamenum": 61,
        "gd": 1,
        "gofo": "3",
        "gr": 24,
        "gyear": "2022",
        "h1": 16,
        "h2": 2,
        "h3": 0,
        "hit": 18,
        "hp": 0,
        "hr": 0,
        "hra": "0.237",
        "hrab": 0,
        "ib": 0,
        "iso": "0.026",
        "kk": 26,
        "kkab": 0,
        "lba": "0.321",
        "lgopo": "0.86",
        "nppa": 4,
        "ops": "0.589",
        "opsPlus": "68.9212",
        "pa": 92,
        "paFlag": "0",
        "pcode": "67005",
        "playerName": "홍현빈",
        "playerPrvwImg": "https://wizzap.ktwiz.co.kr/files/playerImg/ktImg/67005_2024-03-06_140019.jpg",
        "po": 0,
        "rba": "0.34",
        "rbi": 1,
        "rgopo": "0",
        "run": 8,
        "sb": 4,
        "sbTryCn": 4,
        "sba": "1",
        "sf": 0,
        "sh": 6,
        "slab": 0,
        "slg": "0.263",
        "spHra": "0.087",
        "startCn": 24,
        "subCn": 37,
        "teamName": "KT",
        "wrHit": "1"
      },
      {
        "ab": 286,
        "babip": "0.281106",
        "bb": 34,
        "bbhp": 40,
        "bbkk": "0.49",
        "bra": "0.322",
        "cba": "0.164",
        "cgopo": "0.22",
        "cs": 1,
        "fl": 83,
        "gamenum": 112,
        "gd": 9,
        "gofo": "0.88",
        "gr": 73,
        "gyear": "2022",
        "h1": 48,
        "h2": 13,
        "h3": 0,
        "hit": 67,
        "hp": 6,
        "hr": 6,
        "hra": "0.234",
        "hrab": 0,
        "ib": 0,
        "iso": "0.108",
        "kk": 69,
        "kkab": 0,
        "lba": "0.547",
        "lgopo": "2.46",
        "nppa": 3,
        "ops": "0.665",
        "opsPlus": "89.0424",
        "pa": 337,
        "paFlag": "0",
        "pcode": "64504",
        "playerName": "오윤석",
        "playerPrvwImg": "https://wizzap.ktwiz.co.kr/files/playerImg/ktImg/64504_2024-03-06_133239.jpg",
        "po": 0,
        "rba": "0.29",
        "rbi": 37,
        "rgopo": "0.24",
        "run": 23,
        "sb": 2,
        "sbTryCn": 3,
        "sba": "0.667",
        "sf": 6,
        "sh": 5,
        "slab": 0,
        "slg": "0.343",
        "spHra": "0.186",
        "startCn": 86,
        "subCn": 26,
        "teamName": "KT",
        "wrHit": "7"
      },
      {
        "ab": 49,
        "babip": "0.3",
        "bb": 3,
        "bbhp": 3,
        "bbkk": "0.18",
        "bra": "0.269",
        "cba": "0.167",
        "cgopo": "0",
        "cs": 0,
        "fl": 11,
        "gamenum": 28,
        "gd": 2,
        "gofo": "0.91",
        "gr": 10,
        "gyear": "2022",
        "h1": 6,
        "h2": 3,
        "h3": 0,
        "hit": 11,
        "hp": 0,
        "hr": 2,
        "hra": "0.224",
        "hrab": 0,
        "ib": 0,
        "iso": "0.184",
        "kk": 17,
        "kkab": 0,
        "lba": "0.5",
        "lgopo": "5",
        "nppa": 4,
        "ops": "0.677",
        "opsPlus": "90.3152",
        "pa": 52,
        "paFlag": "0",
        "pcode": "64007",
        "playerName": "문상철",
        "playerPrvwImg": "https://wizzap.ktwiz.co.kr/files/playerImg/ktImg/64007_2024-03-06_135143.jpg",
        "po": 0,
        "rba": "0.333",
        "rbi": 4,
        "rgopo": "0",
        "run": 5,
        "sb": 1,
        "sbTryCn": 1,
        "sba": "1",
        "sf": 0,
        "sh": 0,
        "slab": 0,
        "slg": "0.408",
        "spHra": "0.083",
        "startCn": 9,
        "subCn": 19,
        "teamName": "KT",
        "wrHit": "0"
      },
      {
        "ab": 14,
        "babip": "0.375",
        "bb": 1,
        "bbhp": 1,
        "bbkk": "0.17",
        "bra": "0.267",
        "cba": "0.444",
        "cgopo": "0",
        "cs": 0,
        "fl": 3,
        "gamenum": 7,
        "gd": 0,
        "gofo": "0.67",
        "gr": 2,
        "gyear": "2022",
        "h1": 3,
        "h2": 0,
        "h3": 0,
        "hit": 3,
        "hp": 0,
        "hr": 0,
        "hra": "0.214",
        "hrab": 0,
        "ib": 0,
        "iso": "0",
        "kk": 6,
        "kkab": 0,
        "lba": "0.333",
        "lgopo": "0",
        "nppa": 3,
        "ops": "0.481",
        "opsPlus": "37.9758",
        "pa": 16,
        "paFlag": "0",
        "pcode": "51013",
        "playerName": "유준규",
        "playerPrvwImg": "https://wizzap.ktwiz.co.kr/files/playerImg/ktImg/51013_2022-02-18_134517.jpg",
        "po": 0,
        "rba": "0.222",
        "rbi": 0,
        "rgopo": "0",
        "run": 3,
        "sb": 0,
        "sbTryCn": 0,
        "sba": "0",
        "sf": 0,
        "sh": 1,
        "slab": 0,
        "slg": "0.214",
        "spHra": "0.25",
        "startCn": 5,
        "subCn": 2,
        "teamName": "KT",
        "wrHit": "0"
      },
      {
        "ab": 74,
        "babip": "0.291667",
        "bb": 7,
        "bbhp": 10,
        "bbkk": "0.27",
        "bra": "0.294",
        "cba": "0.304",
        "cgopo": "0.11",
        "cs": 3,
        "fl": 20,
        "gamenum": 41,
        "gd": 2,
        "gofo": "0.7",
        "gr": 14,
        "gyear": "2022",
        "h1": 12,
        "h2": 2,
        "h3": 0,
        "hit": 15,
        "hp": 3,
        "hr": 1,
        "hra": "0.203",
        "hrab": 0,
        "ib": 0,
        "iso": "0.068",
        "kk": 26,
        "kkab": 0,
        "lba": "0.5",
        "lgopo": "1.43",
        "nppa": 3,
        "ops": "0.564",
        "opsPlus": "61.0909",
        "pa": 85,
        "paFlag": "0",
        "pcode": "64014",
        "playerName": "김병희",
        "playerPrvwImg": "https://wizzap.ktwiz.co.kr/files/playerImg/ktImg/64014_2023-03-20_103214.jpg",
        "po": 0,
        "rba": "0.196",
        "rbi": 6,
        "rgopo": "0.75",
        "run": 8,
        "sb": 0,
        "sbTryCn": 3,
        "sba": "0",
        "sf": 1,
        "sh": 0,
        "slab": 0,
        "slg": "0.270",
        "spHra": "0.19",
        "startCn": 19,
        "subCn": 22,
        "teamName": "KT",
        "wrHit": "0"
      },
      {
        "ab": 121,
        "babip": "0.225806",
        "bb": 10,
        "bbhp": 12,
        "bbkk": "0.36",
        "bra": "0.254",
        "cba": "0.278",
        "cgopo": "0.55",
        "cs": 1,
        "fl": 32,
        "gamenum": 74,
        "gd": 5,
        "gofo": "1.25",
        "gr": 40,
        "gyear": "2022",
        "h1": 18,
        "h2": 3,
        "h3": 0,
        "hit": 22,
        "hp": 2,
        "hr": 1,
        "hra": "0.182",
        "hrab": 0,
        "ib": 0,
        "iso": "0.05",
        "kk": 28,
        "kkab": 0,
        "lba": "0.367",
        "lgopo": "5.25",
        "nppa": 3,
        "ops": "0.485",
        "opsPlus": "38.5697",
        "pa": 138,
        "paFlag": "0",
        "pcode": "62556",
        "playerName": "신본기",
        "playerPrvwImg": "https://wizzap.ktwiz.co.kr/files/playerImg/ktImg/62556_2024-03-06_133119.jpg",
        "po": 0,
        "rba": "0.356",
        "rbi": 8,
        "rgopo": "0.76",
        "run": 9,
        "sb": 0,
        "sbTryCn": 1,
        "sba": "0",
        "sf": 1,
        "sh": 4,
        "slab": 0,
        "slg": "0.231",
        "spHra": "0.179",
        "startCn": 28,
        "subCn": 46,
        "teamName": "KT",
        "wrHit": "1"
      },
      {
        "ab": 64,
        "babip": "0.222222",
        "bb": 5,
        "bbhp": 5,
        "bbkk": "0.26",
        "bra": "0.217",
        "cba": "0.318",
        "cgopo": "0.33",
        "cs": 2,
        "fl": 15,
        "gamenum": 119,
        "gd": 0,
        "gofo": "1.33",
        "gr": 20,
        "gyear": "2022",
        "h1": 7,
        "h2": 1,
        "h3": 2,
        "hit": 10,
        "hp": 0,
        "hr": 0,
        "hra": "0.156",
        "hrab": 0,
        "ib": 0,
        "iso": "0.078",
        "kk": 19,
        "kkab": 0,
        "lba": "0.455",
        "lgopo": "3.75",
        "nppa": 3,
        "ops": "0.452",
        "opsPlus": "28.1576",
        "pa": 72,
        "paFlag": "0",
        "pcode": "64012",
        "playerName": "송민섭",
        "playerPrvwImg": "https://wizzap.ktwiz.co.kr/files/playerImg/ktImg/64012_2023-03-20_103205.jpg",
        "po": 0,
        "rba": "0.227",
        "rbi": 3,
        "rgopo": "0.6",
        "run": 17,
        "sb": 0,
        "sbTryCn": 2,
        "sba": "0",
        "sf": 0,
        "sh": 3,
        "slab": 0,
        "slg": "0.234",
        "spHra": "0.214",
        "startCn": 5,
        "subCn": 114,
        "teamName": "KT",
        "wrHit": "0"
      },
      {
        "ab": 15,
        "babip": "0.181818",
        "bb": 0,
        "bbhp": 1,
        "bbkk": "0",
        "bra": "0.188",
        "cba": "0.091",
        "cgopo": "0",
        "cs": 0,
        "fl": 3,
        "gamenum": 31,
        "gd": 0,
        "gofo": "2",
        "gr": 6,
        "gyear": "2022",
        "h1": 2,
        "h2": 0,
        "h3": 0,
        "hit": 2,
        "hp": 1,
        "hr": 0,
        "hra": "0.133",
        "hrab": 0,
        "ib": 0,
        "iso": "0",
        "kk": 4,
        "kkab": 0,
        "lba": "0.545",
        "lgopo": "0.67",
        "nppa": 3,
        "ops": "0.321",
        "opsPlus": "-7.56364",
        "pa": 16,
        "paFlag": "0",
        "pcode": "66702",
        "playerName": "이시원",
        "playerPrvwImg": "https://wizzap.ktwiz.co.kr/files/playerImg/ktImg/66702_2023-03-20_103526.jpg",
        "po": 0,
        "rba": "0.364",
        "rbi": 1,
        "rgopo": "0",
        "run": 6,
        "sb": 2,
        "sbTryCn": 2,
        "sba": "1",
        "sf": 0,
        "sh": 0,
        "slab": 0,
        "slg": "0.133",
        "spHra": "0.2",
        "startCn": 2,
        "subCn": 29,
        "teamName": "KT",
        "wrHit": "0"
      },
      {
        "ab": 38,
        "babip": "0.227273",
        "bb": 1,
        "bbhp": 1,
        "bbkk": "0.06",
        "bra": "0.154",
        "cba": "0.188",
        "cgopo": "1",
        "cs": 0,
        "fl": 4,
        "gamenum": 48,
        "gd": 0,
        "gofo": "3.25",
        "gr": 13,
        "gyear": "2022",
        "h1": 3,
        "h2": 1,
        "h3": 1,
        "hit": 5,
        "hp": 0,
        "hr": 0,
        "hra": "0.132",
        "hrab": 0,
        "ib": 0,
        "iso": "0.079",
        "kk": 16,
        "kkab": 0,
        "lba": "0.438",
        "lgopo": "4",
        "nppa": 3,
        "ops": "0.364",
        "opsPlus": "2.93333",
        "pa": 40,
        "paFlag": "0",
        "pcode": "51003",
        "playerName": "권동진",
        "playerPrvwImg": "https://wizzap.ktwiz.co.kr/files/playerImg/ktImg/51003_2024-07-23_110949.jpg",
        "po": 0,
        "rba": "0.375",
        "rbi": 4,
        "rgopo": "7",
        "run": 9,
        "sb": 4,
        "sbTryCn": 4,
        "sba": "1",
        "sf": 0,
        "sh": 1,
        "slab": 0,
        "slg": "0.211",
        "spHra": "0.091",
        "startCn": 8,
        "subCn": 40,
        "teamName": "KT",
        "wrHit": "0"
      },
      {
        "ab": 166,
        "babip": "0.180851",
        "bb": 24,
        "bbhp": 25,
        "bbkk": "0.34",
        "bra": "0.234",
        "cba": "0.247",
        "cgopo": "0.29",
        "cs": 0,
        "fl": 51,
        "gamenum": 100,
        "gd": 3,
        "gofo": "0.51",
        "gr": 26,
        "gyear": "2022",
        "h1": 14,
        "h2": 3,
        "h3": 0,
        "hit": 20,
        "hp": 1,
        "hr": 3,
        "hra": "0.120",
        "hrab": 0,
        "ib": 0,
        "iso": "0.072",
        "kk": 70,
        "kkab": 0,
        "lba": "0.581",
        "lgopo": "0.87",
        "nppa": 4,
        "ops": "0.427",
        "opsPlus": "22.3758",
        "pa": 194,
        "paFlag": "0",
        "pcode": "73113",
        "playerName": "박경수",
        "playerPrvwImg": "https://wizzap.ktwiz.co.kr/files/playerImg/ktImg/73113_2024-03-06_132226.jpg",
        "po": 0,
        "rba": "0.172",
        "rbi": 10,
        "rgopo": "0.14",
        "run": 13,
        "sb": 0,
        "sbTryCn": 0,
        "sba": "0",
        "sf": 1,
        "sh": 2,
        "slab": 0,
        "slg": "0.193",
        "spHra": "0.122",
        "startCn": 47,
        "subCn": 53,
        "teamName": "KT",
        "wrHit": "0"
      },
      {
        "ab": 0,
        "babip": "0",
        "bb": 0,
        "bbhp": 0,
        "bbkk": "0",
        "bra": "0.000",
        "cs": 0,
        "gamenum": 1,
        "gd": 0,
        "gyear": "2022",
        "h1": 0,
        "h2": 0,
        "h3": 0,
        "hit": 0,
        "hp": 0,
        "hr": 0,
        "hra": "0.000",
        "hrab": 0,
        "ib": 0,
        "iso": "0",
        "kk": 0,
        "kkab": 0,
        "nppa": 0,
        "ops": "0",
        "opsPlus": "-100",
        "pa": 0,
        "paFlag": "0",
        "pcode": "68069",
        "playerName": "고명성",
        "playerPrvwImg": "https://wizzap.ktwiz.co.kr/files/playerImg/otherImg/68069_2024-08-07_152042.jpg",
        "rbi": 0,
        "run": 0,
        "sb": 0,
        "sbTryCn": 0,
        "sba": "0",
        "sf": 0,
        "sh": 0,
        "slab": 0,
        "slg": "0.000",
        "startCn": 0,
        "subCn": 1,
        "teamName": "KT",
        "wrHit": "0"
      },
      {
        "ab": 0,
        "babip": "0",
        "bb": 0,
        "bbhp": 0,
        "bbkk": "0",
        "bra": "0.000",
        "cs": 0,
        "gamenum": 1,
        "gd": 0,
        "gyear": "2022",
        "h1": 0,
        "h2": 0,
        "h3": 0,
        "hit": 0,
        "hp": 0,
        "hr": 0,
        "hra": "0.000",
        "hrab": 0,
        "ib": 0,
        "iso": "0",
        "kk": 0,
        "kkab": 0,
        "nppa": 0,
        "ops": "0",
        "opsPlus": "-100",
        "pa": 0,
        "paFlag": "0",
        "pcode": "65062",
        "playerName": "김재윤",
        "playerPrvwImg": "https://wizzap.ktwiz.co.kr/files/playerImg/otherImg/65062_2024-07-26_160350.jpg",
        "rbi": 0,
        "run": 0,
        "sb": 0,
        "sbTryCn": 0,
        "sba": "0",
        "sf": 0,
        "sh": 0,
        "slab": 0,
        "slg": "0.000",
        "startCn": 0,
        "subCn": 1,
        "teamName": "KT",
        "wrHit": "0"
      },
      {
        "ab": 10,
        "babip": "0",
        "bb": 0,
        "bbhp": 0,
        "bbkk": "0",
        "bra": "0.000",
        "cba": "0",
        "cgopo": "0",
        "cs": 0,
        "fl": 5,
        "gamenum": 7,
        "gd": 0,
        "gofo": "0.6",
        "gr": 3,
        "gyear": "2022",
        "h1": 0,
        "h2": 0,
        "h3": 0,
        "hit": 0,
        "hp": 0,
        "hr": 0,
        "hra": "0.000",
        "hrab": 0,
        "ib": 0,
        "iso": "0",
        "kk": 2,
        "kkab": 0,
        "lba": "0.375",
        "lgopo": "0",
        "nppa": 3,
        "ops": "0",
        "opsPlus": "-100",
        "pa": 10,
        "paFlag": "0",
        "pcode": "65040",
        "playerName": "김태훈",
        "playerPrvwImg": "https://wizzap.ktwiz.co.kr/files/playerImg/otherImg/65040_2024-07-26_160339.jpg",
        "po": 0,
        "rba": "0.625",
        "rbi": 0,
        "rgopo": "1.5",
        "run": 0,
        "sb": 0,
        "sbTryCn": 0,
        "sba": "0",
        "sf": 0,
        "sh": 0,
        "slab": 0,
        "slg": "0.000",
        "spHra": "0",
        "startCn": 1,
        "subCn": 6,
        "teamName": "KT",
        "wrHit": "0"
      },
      {
        "ab": 3,
        "babip": "0",
        "bb": 0,
        "bbhp": 0,
        "bbkk": "0",
        "bra": "0.000",
        "cba": "0",
        "cgopo": "0",
        "cs": 0,
        "fl": 0,
        "gamenum": 12,
        "gd": 1,
        "gofo": "0",
        "gr": 1,
        "gyear": "2022",
        "h1": 0,
        "h2": 0,
        "h3": 0,
        "hit": 0,
        "hp": 0,
        "hr": 0,
        "hra": "0.000",
        "hrab": 0,
        "ib": 0,
        "iso": "0",
        "kk": 2,
        "kkab": 0,
        "lba": "1",
        "lgopo": "0",
        "nppa": 3,
        "ops": "0",
        "opsPlus": "-100",
        "pa": 3,
        "paFlag": "0",
        "pcode": "67063",
        "playerName": "문상인",
        "playerPrvwImg": "https://wizzap.ktwiz.co.kr/files/playerImg/ktImg/67063_2023-03-20_103646.jpg",
        "po": 0,
        "rba": "0",
        "rbi": 0,
        "rgopo": "0",
        "run": 2,
        "sb": 0,
        "sbTryCn": 0,
        "sba": "0",
        "sf": 0,
        "sh": 0,
        "slab": 0,
        "slg": "0.000",
        "spHra": "0",
        "startCn": 0,
        "subCn": 12,
        "teamName": "KT",
        "wrHit": "0"
      },
      {
        "ab": 0,
        "babip": "0",
        "bb": 0,
        "bbhp": 0,
        "bbkk": "0",
        "bra": "0.000",
        "cs": 0,
        "gamenum": 4,
        "gd": 0,
        "gyear": "2022",
        "h1": 0,
        "h2": 0,
        "h3": 0,
        "hit": 0,
        "hp": 0,
        "hr": 0,
        "hra": "0.000",
        "hrab": 0,
        "ib": 0,
        "iso": "0",
        "kk": 0,
        "kkab": 0,
        "nppa": 0,
        "ops": "0",
        "opsPlus": "-100",
        "pa": 0,
        "paFlag": "0",
        "pcode": "52060",
        "playerName": "박영현",
        "playerPrvwImg": "https://wizzap.ktwiz.co.kr/files/playerImg/ktImg/52060_2024-03-06_121312.jpg",
        "rbi": 0,
        "run": 0,
        "sb": 0,
        "sbTryCn": 0,
        "sba": "0",
        "sf": 0,
        "sh": 0,
        "slab": 0,
        "slg": "0.000",
        "startCn": 0,
        "subCn": 4,
        "teamName": "KT",
        "wrHit": "0"
      },
      {
        "ab": 0,
        "babip": "0",
        "bb": 0,
        "bbhp": 0,
        "bbkk": "0",
        "bra": "0.000",
        "cs": 0,
        "gamenum": 1,
        "gd": 0,
        "gyear": "2022",
        "h1": 0,
        "h2": 0,
        "h3": 0,
        "hit": 0,
        "hp": 0,
        "hr": 0,
        "hra": "0.000",
        "hrab": 0,
        "ib": 0,
        "iso": "0",
        "kk": 0,
        "kkab": 0,
        "nppa": 0,
        "ops": "0",
        "opsPlus": "-100",
        "pa": 0,
        "paFlag": "0",
        "pcode": "65516",
        "playerName": "배제성",
        "playerPrvwImg": "https://wizzap.ktwiz.co.kr/files/playerImg/ktImg/65516_2023-03-20_103432.jpg",
        "rbi": 0,
        "run": 0,
        "sb": 0,
        "sbTryCn": 0,
        "sba": "0",
        "sf": 0,
        "sh": 0,
        "slab": 0,
        "slg": "0.000",
        "startCn": 0,
        "subCn": 1,
        "teamName": "KT",
        "wrHit": "0"
      },
      {
        "ab": 0,
        "babip": "0",
        "bb": 0,
        "bbhp": 0,
        "bbkk": "0",
        "bra": "0.000",
        "cs": 0,
        "gamenum": 2,
        "gd": 0,
        "gyear": "2022",
        "h1": 0,
        "h2": 0,
        "h3": 0,
        "hit": 0,
        "hp": 0,
        "hr": 0,
        "hra": "0.000",
        "hrab": 0,
        "ib": 0,
        "iso": "0",
        "kk": 0,
        "kkab": 0,
        "nppa": 0,
        "ops": "0",
        "opsPlus": "-100",
        "pa": 0,
        "paFlag": "0",
        "pcode": "64017",
        "playerName": "심재민",
        "playerPrvwImg": "https://wizzap.ktwiz.co.kr/files/playerImg/otherImg/64017_2024-08-09_142705.jpg",
        "rbi": 0,
        "run": 0,
        "sb": 0,
        "sbTryCn": 0,
        "sba": "0",
        "sf": 0,
        "sh": 0,
        "slab": 0,
        "slg": "0.000",
        "startCn": 0,
        "subCn": 2,
        "teamName": "KT",
        "wrHit": "0"
      },
      {
        "ab": 5,
        "babip": "0",
        "bb": 0,
        "bbhp": 0,
        "bbkk": "0",
        "bra": "0.000",
        "cba": "0",
        "cgopo": "0",
        "cs": 1,
        "fl": 1,
        "gamenum": 11,
        "gd": 0,
        "gofo": "3",
        "gr": 3,
        "gyear": "2022",
        "h1": 0,
        "h2": 0,
        "h3": 0,
        "hit": 0,
        "hp": 0,
        "hr": 0,
        "hra": "0.000",
        "hrab": 0,
        "ib": 0,
        "iso": "0",
        "kk": 1,
        "kkab": 0,
        "lba": "0.5",
        "lgopo": "1",
        "nppa": 3,
        "ops": "0",
        "opsPlus": "-100",
        "pa": 5,
        "paFlag": "0",
        "pcode": "68002",
        "playerName": "양승혁",
        "playerPrvwImg": "https://wizzap.ktwiz.co.kr/files/playerImg/ktImg/68002_2024-03-08_104352.jpg",
        "po": 0,
        "rba": "0.5",
        "rbi": 0,
        "rgopo": "0",
        "run": 0,
        "sb": 1,
        "sbTryCn": 2,
        "sba": "0.5",
        "sf": 0,
        "sh": 0,
        "slab": 0,
        "slg": "0.000",
        "spHra": "0",
        "startCn": 2,
        "subCn": 9,
        "teamName": "KT",
        "wrHit": "0"
      },
      {
        "ab": 0,
        "babip": "0",
        "bb": 0,
        "bbhp": 0,
        "bbkk": "0",
        "bra": "0.000",
        "cs": 0,
        "gamenum": 1,
        "gd": 0,
        "gyear": "2022",
        "h1": 0,
        "h2": 0,
        "h3": 0,
        "hit": 0,
        "hp": 0,
        "hr": 0,
        "hra": "0.000",
        "hrab": 0,
        "ib": 0,
        "iso": "0",
        "kk": 0,
        "kkab": 0,
        "nppa": 0,
        "ops": "0",
        "opsPlus": "-100",
        "pa": 0,
        "paFlag": "0",
        "pcode": "52063",
        "playerName": "이상우",
        "playerPrvwImg": "https://wizzap.ktwiz.co.kr/files/playerImg/ktImg/52063_2023-03-20_102329.jpg",
        "rbi": 0,
        "run": 0,
        "sb": 0,
        "sbTryCn": 0,
        "sba": "0",
        "sf": 0,
        "sh": 0,
        "slab": 0,
        "slg": "0.000",
        "startCn": 0,
        "subCn": 1,
        "teamName": "KT",
        "wrHit": "0"
      },
      {
        "ab": 0,
        "babip": "0",
        "bb": 0,
        "bbhp": 0,
        "bbkk": "0",
        "bra": "0.000",
        "cs": 0,
        "gamenum": 1,
        "gd": 0,
        "gyear": "2022",
        "h1": 0,
        "h2": 0,
        "h3": 0,
        "hit": 0,
        "hp": 0,
        "hr": 0,
        "hra": "0.000",
        "hrab": 0,
        "ib": 0,
        "iso": "0",
        "kk": 0,
        "kkab": 0,
        "nppa": 0,
        "ops": "0",
        "opsPlus": "-100",
        "pa": 0,
        "paFlag": "0",
        "pcode": "67048",
        "playerName": "이정현",
        "playerPrvwImg": "https://wizzap.ktwiz.co.kr/files/playerImg/ktImg/67048_2024-03-06_123938.jpg",
        "rbi": 0,
        "run": 0,
        "sb": 0,
        "sbTryCn": 0,
        "sba": "0",
        "sf": 0,
        "sh": 0,
        "slab": 0,
        "slg": "0.000",
        "startCn": 0,
        "subCn": 1,
        "teamName": "KT",
        "wrHit": "0"
      },
      {
        "ab": 4,
        "babip": "0",
        "bb": 0,
        "bbhp": 0,
        "bbkk": "0",
        "bra": "0.000",
        "cba": "0",
        "cgopo": "0",
        "cs": 0,
        "fl": 0,
        "gamenum": 6,
        "gd": 0,
        "gofo": "0",
        "gr": 1,
        "gyear": "2022",
        "h1": 0,
        "h2": 0,
        "h3": 0,
        "hit": 0,
        "hp": 0,
        "hr": 0,
        "hra": "0.000",
        "hrab": 0,
        "ib": 0,
        "iso": "0",
        "kk": 3,
        "kkab": 0,
        "lba": "1",
        "lgopo": "0",
        "nppa": 4,
        "ops": "0",
        "opsPlus": "-100",
        "pa": 4,
        "paFlag": "0",
        "pcode": "68089",
        "playerName": "조대현",
        "playerPrvwImg": "https://wizzap.ktwiz.co.kr/files/playerImg/ktImg/68089_2024-03-08_104729.jpg",
        "po": 0,
        "rba": "0",
        "rbi": 0,
        "rgopo": "0",
        "run": 0,
        "sb": 0,
        "sbTryCn": 0,
        "sba": "0",
        "sf": 0,
        "sh": 0,
        "slab": 0,
        "slg": "0.000",
        "spHra": "0",
        "startCn": 0,
        "subCn": 6,
        "teamName": "KT",
        "wrHit": "0"
      },
      {
        "ab": 0,
        "babip": "0",
        "bb": 0,
        "bbhp": 0,
        "bbkk": "0",
        "bra": "0.000",
        "cs": 0,
        "gamenum": 1,
        "gd": 0,
        "gyear": "2022",
        "h1": 0,
        "h2": 0,
        "h3": 0,
        "hit": 0,
        "hp": 0,
        "hr": 0,
        "hra": "0.000",
        "hrab": 0,
        "ib": 0,
        "iso": "0",
        "kk": 0,
        "kkab": 0,
        "nppa": 0,
        "ops": "0",
        "opsPlus": "-100",
        "pa": 0,
        "paFlag": "0",
        "pcode": "65060",
        "playerName": "주권",
        "playerPrvwImg": "https://wizzap.ktwiz.co.kr/files/playerImg/ktImg/65060_2024-03-06_124951.jpg",
        "rbi": 0,
        "run": 0,
        "sb": 0,
        "sbTryCn": 0,
        "sba": "0",
        "sf": 0,
        "sh": 0,
        "slab": 0,
        "slg": "0.000",
        "startCn": 0,
        "subCn": 1,
        "teamName": "KT",
        "wrHit": "0"
      },
      {
        "ab": 0,
        "babip": "0",
        "bb": 0,
        "bbhp": 0,
        "bbkk": "0",
        "bra": "0.000",
        "cs": 0,
        "gamenum": 1,
        "gd": 0,
        "gyear": "2022",
        "h1": 0,
        "h2": 0,
        "h3": 0,
        "hit": 0,
        "hp": 0,
        "hr": 0,
        "hra": "0.000",
        "hrab": 0,
        "ib": 0,
        "iso": "0",
        "kk": 0,
        "kkab": 0,
        "nppa": 0,
        "ops": "0",
        "opsPlus": "-100",
        "pa": 0,
        "paFlag": "0",
        "pcode": "51060",
        "playerName": "지명성",
        "playerPrvwImg": "https://wizzap.ktwiz.co.kr/files/playerImg/ktImg/51060_2022-02-18_135210.jpg",
        "rbi": 0,
        "run": 0,
        "sb": 0,
        "sbTryCn": 0,
        "sba": "0",
        "sf": 0,
        "sh": 0,
        "slab": 0,
        "slg": "0.000",
        "startCn": 0,
        "subCn": 1,
        "teamName": "KT",
        "wrHit": "0"
      }
    ]
  }
}